{"performance": 0.3749, "config_list": "[{\"op_types\": [\"Conv2d\"], \"sparsity\": 0.12493707625201111, \"op_names\": [\"layer2.0.downsample.0\"]}, {\"op_types\": [\"Conv2d\"], \"sparsity\": 0.14881865724415116, \"op_names\": [\"conv1\"]}, {\"op_types\": [\"Conv2d\"], \"sparsity\": 0.22210495474974337, \"op_names\": [\"layer3.0.downsample.0\"]}, {\"op_types\": [\"Conv2d\"], \"sparsity\": 0.23476022293188667, \"op_names\": [\"layer1.0.conv1\"]}, {\"op_types\": [\"Conv2d\"], \"sparsity\": 0.277568389783211, \"op_names\": [\"layer1.0.conv2\"]}, {\"op_types\": [\"Conv2d\"], \"sparsity\": 0.306537609230035, \"op_names\": [\"layer1.1.conv1\"]}, {\"op_types\": [\"Conv2d\"], \"sparsity\": 0.3510160267929741, \"op_names\": [\"layer1.1.conv2\"]}, {\"op_types\": [\"Conv2d\"], \"sparsity\": 0.6191692079666151, \"op_names\": [\"layer2.0.conv1\"]}, {\"op_types\": [\"Conv2d\"], \"sparsity\": 0.6575447140267985, \"op_names\": [\"layer4.1.conv1\"]}, {\"op_types\": [\"Conv2d\"], \"sparsity\": 0.6701532630256286, \"op_names\": [\"layer4.1.conv2\"]}, {\"op_types\": [\"Conv2d\"], \"sparsity\": 0.6831728177849619, \"op_names\": [\"layer2.1.conv1\"]}, {\"op_types\": [\"Conv2d\"], \"sparsity\": 0.7339585041078462, \"op_names\": [\"layer2.1.conv2\"]}, {\"op_types\": [\"Conv2d\"], \"sparsity\": 0.7695464399731234, \"op_names\": [\"layer3.0.conv1\"]}, {\"op_types\": [\"Conv2d\"], \"sparsity\": 0.7902829800266785, \"op_names\": [\"layer4.0.conv1\"]}, {\"op_types\": [\"Conv2d\"], \"sparsity\": 0.8166723250359432, \"op_names\": [\"layer4.0.conv2\"]}, {\"op_types\": [\"Conv2d\"], \"sparsity\": 0.8189308327038748, \"op_names\": [\"layer4.0.downsample.0\"]}, {\"op_types\": [\"Conv2d\"], \"sparsity\": 0.8411830759034101, \"op_names\": [\"layer2.0.conv2\"]}, {\"op_types\": [\"Conv2d\"], \"sparsity\": 0.8553561450500203, \"op_names\": [\"layer3.1.conv1\"]}, {\"op_types\": [\"Conv2d\"], \"sparsity\": 0.8555350180058503, \"op_names\": [\"layer3.1.conv2\"]}, {\"op_types\": [\"Conv2d\"], \"sparsity\": 0.9410680207407564, \"op_names\": [\"layer3.0.conv2\"]}]"}